source_optimizer/__init__.py
source_optimizer/cli.py
source_optimizer/source_optimizer.py
source_optimizer-0.1.0.dist-info/AUTHORS.rst
source_optimizer-0.1.0.dist-info/LICENSE
source_optimizer-0.1.0.dist-info/METADATA
source_optimizer-0.1.0.dist-info/WHEEL
source_optimizer-0.1.0.dist-info/entry_points.txt
source_optimizer-0.1.0.dist-info/top_level.txt
source_optimizer-0.1.0.dist-info/RECORD
