Metadata-Version: 2.1
Name: source-optimizer
Version: 0.1.0
Summary: A python source code optimizer
Home-page: https://github.com/vMarcelino/source_optimizer
Author: Victor Fernandes Mariano Marcelino
Author-email: victor.fmarcelino@gmail.com
License: MIT license
Keywords: source_optimizer
Platform: UNKNOWN
Classifier: Development Status :: 2 - Pre-Alpha
Classifier: Intended Audience :: Developers
Classifier: License :: OSI Approved :: MIT License
Classifier: Natural Language :: English
Classifier: Programming Language :: Python :: 3
Classifier: Programming Language :: Python :: 3.5
Classifier: Programming Language :: Python :: 3.6
Classifier: Programming Language :: Python :: 3.7
Classifier: Programming Language :: Python :: 3.8
Requires-Python: >=3.5
Requires-Dist: Click (>=7.0)
